condu/__init__.py
condu/condu.py
condu/conductor.py
condu/objects.py
condu-2.0.0b7.dist-info/DESCRIPTION.rst
condu-2.0.0b7.dist-info/METADATA
condu-2.0.0b7.dist-info/RECORD
condu-2.0.0b7.dist-info/WHEEL
condu-2.0.0b7.dist-info/metadata.json
condu-2.0.0b7.dist-info/top_level.txt
tests/client_termination/__init__.py
tests/client_termination/test_client_termination.py
tests/metadata_testing/__init__.py
tests/metadata_testing/test_metadata.py
tests/metadata_testing/test_utils.py
tests/task_poll_execution/__init__.py
tests/task_poll_execution/test_task_poll_with_ack.py
tests/worker_process_killed_by_os/__init__.py
tests/worker_process_killed_by_os/test_worker_process_kill.py
