Metadata-Version: 2.0
Name: condu
Version: 2.0.0b7
Summary: Conductor client
Home-page: https://github.com/bioslikk/condu/
Author: Bruno Lopes
Author-email: brunoleonelopes@gmail.com
License: Apache 2.0
Keywords: client for conductor
Platform: UNKNOWN
Classifier: Development Status :: 4 - Beta
Classifier: Intended Audience :: Developers
Classifier: Intended Audience :: System Administrators
Classifier: License :: OSI Approved :: Apache Software License
Classifier: Programming Language :: Python :: 3.6
Classifier: Topic :: Internet
Classifier: Topic :: Software Development :: Libraries :: Python Modules
Classifier: Topic :: System :: Networking
Requires-Python: >=3.4
Requires-Dist: requests
